{
    "1": {
        "hp": 0,
        "atk": 1,
        "def": 0,
        "spe": 0
    },
    "4": {
        "hp": 0,
        "atk": 1,
        "def": 0,
        "spe": 0
    },
    "7": {
        "hp": 0,
        "atk": 1,
        "def": 0,
        "spe": 0
    },
    "10": {
        "hp": 0,
        "atk": 1,
        "def": 0,
        "spe": 0
    },
    "12": {
        "hp": 0,
        "atk": 1,
        "def": 0,
        "spe": 0
    },
    "15": {
        "hp": 0,
        "atk": 1,
        "def": 0,
        "spe": 0
    },
    "18": {
        "hp": 2,
        "atk": 0,
        "def": 0,
        "spe": 0
    },
    "21": {
        "hp": 0,
        "atk": 0,
        "def": 0,
        "spe": 2
    }
}